{
    "id": "523",
    "National №": "523",
    "Type": [
        "Electric"
    ],
    "Species": "Thunderbolt Pokémon",
    "Height": "5′3″ (1.60m)",
    "Weight": "175.3 lbs (79.5 kg)",
    "Abilities": [
        "Lightning Rod",
        "Motor Drive"
    ],
    "Local №": [],
    "Japanese": "Zeburaika",
    "stats": {
        "HP": {
            "avg": "75",
            "min": "260",
            "max": "354"
        },
        "Attack": {
            "avg": "100",
            "min": "184",
            "max": "328"
        },
        "Defense": {
            "avg": "63",
            "min": "117",
            "max": "247"
        },
        "Sp. Atk": {
            "avg": "80",
            "min": "148",
            "max": "284"
        },
        "Sp. Def": {
            "avg": "63",
            "min": "117",
            "max": "247"
        },
        "Speed": {
            "avg": "116",
            "min": "213",
            "max": "364"
        }
    },
    "typeDef": {},
    "description": "They have lightning-like movements. When Zebstrika run at full speed, the sound of thunder reverberates.",
    "moves": {
        "0": {
            "title": "Moves learnt by level up",
            "Lv.": [
                "1",
                "1",
                "1",
                "1",
                "1",
                "4",
                "8",
                "11",
                "15",
                "18",
                "22",
                "25",
                "31",
                "36",
                "42",
                "47",
                "53",
                "58"
            ],
            "Move": [
                "Charge",
                "Ion Deluge",
                "Quick Attack",
                "Tail Whip",
                "Thunder Wave",
                "Tail Whip",
                "Charge",
                "Shock Wave",
                "Thunder Wave",
                "Flame Charge",
                "Pursuit",
                "Spark",
                "Stomp",
                "Discharge",
                "Agility",
                "Wild Charge",
                "Thrash",
                "Ion Deluge"
            ],
            "Type": [
                "Electric",
                "Electric",
                "Normal",
                "Normal",
                "Electric",
                "Normal",
                "Electric",
                "Electric",
                "Electric",
                "Fire",
                "Dark",
                "Electric",
                "Normal",
                "Electric",
                "Psychic",
                "Electric",
                "Normal",
                "Electric"
            ],
            "Cat.": [
                "Status",
                "Status",
                "Physical",
                "Status",
                "Status",
                "Status",
                "Status",
                "Special",
                "Status",
                "Physical",
                "Physical",
                "Physical",
                "Physical",
                "Special",
                "Status",
                "Physical",
                "Physical",
                "Status"
            ],
            "Power": [
                "-",
                "-",
                "40",
                "-",
                "-",
                "-",
                "-",
                "60",
                "-",
                "50",
                "40",
                "65",
                "65",
                "80",
                "-",
                "90",
                "120",
                "-"
            ],
            "Acc.": [
                "-",
                "-",
                "100",
                "100",
                "100",
                "100",
                "-",
                "∞",
                "100",
                "100",
                "100",
                "100",
                "100",
                "100",
                "-",
                "100",
                "100",
                "-"
            ],
            "set": [
                "Lv.",
                "Move",
                "Type",
                "Cat.",
                "Power",
                "Acc."
            ]
        },
        "1": {
            "title": "Egg moves",
            "Move": [
                "Double-Edge",
                "Double Kick",
                "Endure",
                "Me First",
                "Rage",
                "Sand Attack",
                "Screech",
                "Shock Wave",
                "Snatch",
                "Take Down"
            ],
            "Type": [
                "Normal",
                "Fighting",
                "Normal",
                "Normal",
                "Normal",
                "Ground",
                "Normal",
                "Electric",
                "Dark",
                "Normal"
            ],
            "Cat.": [
                "Physical",
                "Physical",
                "Status",
                "Status",
                "Physical",
                "Status",
                "Status",
                "Special",
                "Status",
                "Physical"
            ],
            "Power": [
                "120",
                "30",
                "-",
                "-",
                "20",
                "-",
                "-",
                "60",
                "-",
                "90"
            ],
            "Acc.": [
                "100",
                "100",
                "-",
                "-",
                "100",
                "100",
                "85",
                "∞",
                "-",
                "85"
            ],
            "set": [
                "Move",
                "Type",
                "Cat.",
                "Power",
                "Acc."
            ]
        },
        "2": {
            "title": "Moves learnt by HM",
            "set": []
        },
        "3": {
            "title": "Moves learnt by TM",
            "TM": [
                "6",
                "10",
                "15",
                "16",
                "17",
                "18",
                "21",
                "24",
                "25",
                "27",
                "32",
                "42",
                "43",
                "44",
                "45",
                "48",
                "50",
                "57",
                "68",
                "70",
                "72",
                "73",
                "87",
                "88",
                "90",
                "93",
                "94",
                "100"
            ],
            "Move": [
                "Toxic",
                "Hidden Power",
                "Hyper Beam",
                "Light Screen",
                "Protect",
                "Rain Dance",
                "Frustration",
                "Thunderbolt",
                "Thunder",
                "Return",
                "Double Team",
                "Facade",
                "Flame Charge",
                "Rest",
                "Attract",
                "Round",
                "Overheat",
                "Charge Beam",
                "Giga Impact",
                "Flash",
                "Volt Switch",
                "Thunder Wave",
                "Swagger",
                "Sleep Talk",
                "Substitute",
                "Wild Charge",
                "Rock Smash",
                "Confide"
            ],
            "Type": [
                "Poison",
                "Normal",
                "Normal",
                "Psychic",
                "Normal",
                "Water",
                "Normal",
                "Electric",
                "Electric",
                "Normal",
                "Normal",
                "Normal",
                "Fire",
                "Psychic",
                "Normal",
                "Normal",
                "Fire",
                "Electric",
                "Normal",
                "Normal",
                "Electric",
                "Electric",
                "Normal",
                "Normal",
                "Normal",
                "Electric",
                "Fighting",
                "Normal"
            ],
            "Cat.": [
                "Status",
                "Special",
                "Special",
                "Status",
                "Status",
                "Status",
                "Physical",
                "Special",
                "Special",
                "Physical",
                "Status",
                "Physical",
                "Physical",
                "Status",
                "Status",
                "Special",
                "Special",
                "Special",
                "Physical",
                "Status",
                "Special",
                "Status",
                "Status",
                "Status",
                "Status",
                "Physical",
                "Physical",
                "Status"
            ],
            "Power": [
                "-",
                "60",
                "150",
                "-",
                "-",
                "-",
                "-",
                "90",
                "110",
                "-",
                "-",
                "70",
                "50",
                "-",
                "-",
                "60",
                "130",
                "50",
                "150",
                "-",
                "70",
                "-",
                "-",
                "-",
                "-",
                "90",
                "40",
                "-"
            ],
            "Acc.": [
                "90",
                "100",
                "90",
                "-",
                "-",
                "-",
                "100",
                "100",
                "70",
                "100",
                "-",
                "100",
                "100",
                "-",
                "100",
                "100",
                "90",
                "90",
                "90",
                "100",
                "100",
                "100",
                "90",
                "-",
                "-",
                "100",
                "100",
                "-"
            ],
            "set": [
                "TM",
                "Move",
                "Type",
                "Cat.",
                "Power",
                "Acc."
            ]
        }
    },
    "locations": [
        {
            "BlackWhite": [
                "Route 7"
            ],
            "Black 2White 2": [
                "Route 3",
                "7"
            ],
            "Omega RubyAlpha Sapphire": [
                "Mirage Spots"
            ]
        }
    ]
}