{
    "id": "243",
    "National №": "243",
    "Type": [
        "Electric"
    ],
    "Species": "Thunder Pokémon",
    "Height": "6′3″ (1.91m)",
    "Weight": "392.4 lbs (178.0 kg)",
    "Abilities": [
        "Pressure"
    ],
    "Local №": [],
    "stats": {
        "HP": {
            "avg": "90",
            "min": "290",
            "max": "384"
        },
        "Attack": {
            "avg": "85",
            "min": "157",
            "max": "295"
        },
        "Defense": {
            "avg": "75",
            "min": "139",
            "max": "273"
        },
        "Sp. Atk": {
            "avg": "115",
            "min": "211",
            "max": "361"
        },
        "Sp. Def": {
            "avg": "100",
            "min": "184",
            "max": "328"
        },
        "Speed": {
            "avg": "115",
            "min": "211",
            "max": "361"
        }
    },
    "typeDef": {},
    "description": "This rough Pokémon stores energy inside its body, then sweeps across the land, shooting off electricity.",
    "moves": {
        "0": {
            "title": "Moves learnt by level up",
            "Lv.": [
                "1",
                "1",
                "1",
                "1",
                "8",
                "15",
                "22",
                "29",
                "36",
                "43",
                "50",
                "57",
                "64",
                "71",
                "78",
                "85"
            ],
            "Move": [
                "Bite",
                "Discharge",
                "Extrasensory",
                "Leer",
                "Thunder Shock",
                "Roar",
                "Quick Attack",
                "Spark",
                "Reflect",
                "Crunch",
                "Thunder Fang",
                "Discharge",
                "Extrasensory",
                "Rain Dance",
                "Calm Mind",
                "Thunder"
            ],
            "Type": [
                "Dark",
                "Electric",
                "Psychic",
                "Normal",
                "Electric",
                "Normal",
                "Normal",
                "Electric",
                "Psychic",
                "Dark",
                "Electric",
                "Electric",
                "Psychic",
                "Water",
                "Psychic",
                "Electric"
            ],
            "Cat.": [
                "Physical",
                "Special",
                "Special",
                "Status",
                "Special",
                "Status",
                "Physical",
                "Physical",
                "Status",
                "Physical",
                "Physical",
                "Special",
                "Special",
                "Status",
                "Status",
                "Special"
            ],
            "Power": [
                "60",
                "80",
                "80",
                "-",
                "40",
                "-",
                "40",
                "65",
                "-",
                "80",
                "65",
                "80",
                "80",
                "-",
                "-",
                "110"
            ],
            "Acc.": [
                "100",
                "100",
                "100",
                "100",
                "100",
                "-",
                "100",
                "100",
                "-",
                "100",
                "95",
                "100",
                "100",
                "-",
                "-",
                "70"
            ],
            "set": [
                "Lv.",
                "Move",
                "Type",
                "Cat.",
                "Power",
                "Acc."
            ]
        },
        "1": {
            "title": "Egg moves",
            "set": []
        },
        "2": {
            "title": "Moves learnt by HM",
            "HM": [
                "1",
                "4"
            ],
            "Move": [
                "Cut",
                "Strength"
            ],
            "Type": [
                "Normal",
                "Normal"
            ],
            "Cat.": [
                "Physical",
                "Physical"
            ],
            "Power": [
                "50",
                "80"
            ],
            "Acc.": [
                "95",
                "100"
            ],
            "set": [
                "HM",
                "Move",
                "Type",
                "Cat.",
                "Power",
                "Acc."
            ]
        },
        "3": {
            "title": "Moves learnt by TM",
            "TM": [
                "4",
                "5",
                "6",
                "10",
                "11",
                "15",
                "16",
                "17",
                "18",
                "21",
                "24",
                "25",
                "27",
                "28",
                "30",
                "32",
                "33",
                "37",
                "42",
                "44",
                "48",
                "57",
                "60",
                "68",
                "70",
                "72",
                "73",
                "77",
                "78",
                "87",
                "88",
                "90",
                "93",
                "94",
                "95",
                "100"
            ],
            "Move": [
                "Calm Mind",
                "Roar",
                "Toxic",
                "Hidden Power",
                "Sunny Day",
                "Hyper Beam",
                "Light Screen",
                "Protect",
                "Rain Dance",
                "Frustration",
                "Thunderbolt",
                "Thunder",
                "Return",
                "Dig",
                "Shadow Ball",
                "Double Team",
                "Reflect",
                "Sandstorm",
                "Facade",
                "Rest",
                "Round",
                "Charge Beam",
                "Quash",
                "Giga Impact",
                "Flash",
                "Volt Switch",
                "Thunder Wave",
                "Psych Up",
                "Bulldoze",
                "Swagger",
                "Sleep Talk",
                "Substitute",
                "Wild Charge",
                "Rock Smash",
                "Snarl",
                "Confide"
            ],
            "Type": [
                "Psychic",
                "Normal",
                "Poison",
                "Normal",
                "Fire",
                "Normal",
                "Psychic",
                "Normal",
                "Water",
                "Normal",
                "Electric",
                "Electric",
                "Normal",
                "Ground",
                "Ghost",
                "Normal",
                "Psychic",
                "Rock",
                "Normal",
                "Psychic",
                "Normal",
                "Electric",
                "Dark",
                "Normal",
                "Normal",
                "Electric",
                "Electric",
                "Normal",
                "Ground",
                "Normal",
                "Normal",
                "Normal",
                "Electric",
                "Fighting",
                "Dark",
                "Normal"
            ],
            "Cat.": [
                "Status",
                "Status",
                "Status",
                "Special",
                "Status",
                "Special",
                "Status",
                "Status",
                "Status",
                "Physical",
                "Special",
                "Special",
                "Physical",
                "Physical",
                "Special",
                "Status",
                "Status",
                "Status",
                "Physical",
                "Status",
                "Special",
                "Special",
                "Status",
                "Physical",
                "Status",
                "Special",
                "Status",
                "Status",
                "Physical",
                "Status",
                "Status",
                "Status",
                "Physical",
                "Physical",
                "Special",
                "Status"
            ],
            "Power": [
                "-",
                "-",
                "-",
                "60",
                "-",
                "150",
                "-",
                "-",
                "-",
                "-",
                "90",
                "110",
                "-",
                "80",
                "80",
                "-",
                "-",
                "-",
                "70",
                "-",
                "60",
                "50",
                "-",
                "150",
                "-",
                "70",
                "-",
                "-",
                "60",
                "-",
                "-",
                "-",
                "90",
                "40",
                "55",
                "-"
            ],
            "Acc.": [
                "-",
                "-",
                "90",
                "100",
                "-",
                "90",
                "-",
                "-",
                "-",
                "100",
                "100",
                "70",
                "100",
                "100",
                "100",
                "-",
                "-",
                "-",
                "100",
                "-",
                "100",
                "90",
                "100",
                "90",
                "100",
                "100",
                "100",
                "-",
                "100",
                "90",
                "-",
                "-",
                "100",
                "100",
                "95",
                "-"
            ],
            "set": [
                "TM",
                "Move",
                "Type",
                "Cat.",
                "Power",
                "Acc."
            ]
        },
        "4": {
            "title": "Transfer-only moves",
            "Move": [
                "Body Slam",
                "Double-Edge",
                "Mimic",
                "Natural Gift",
                "Rock Climb",
                "Headbutt",
                "Mud-Slap",
                "Swift",
                "Aura Sphere",
                "Extreme Speed",
                "Weather Ball",
                "Zap Cannon"
            ],
            "Type": [
                "Normal",
                "Normal",
                "Normal",
                "Normal",
                "Normal",
                "Normal",
                "Ground",
                "Normal",
                "Fighting",
                "Normal",
                "Normal",
                "Electric"
            ],
            "Cat.": [
                "Physical",
                "Physical",
                "Status",
                "Physical",
                "Physical",
                "Physical",
                "Special",
                "Special",
                "Special",
                "Physical",
                "Special",
                "Special"
            ],
            "Power": [
                "85",
                "120",
                "-",
                "-",
                "90",
                "70",
                "20",
                "60",
                "80",
                "80",
                "50",
                "120"
            ],
            "Acc.": [
                "100",
                "100",
                "-",
                "100",
                "85",
                "100",
                "100",
                "∞",
                "∞",
                "100",
                "100",
                "50"
            ],
            "Method": [
                "Generation 3 — Move tutor",
                "Generation 3 — Move tutor",
                "Generation 3 — Move tutor",
                "Generation 4 — TM",
                "Generation 4 — HM",
                "Generation 4 — Move tutor",
                "Generation 4 — Move tutor",
                "Generation 4 — Move tutor",
                "Generation 4 — Special",
                "Generation 4 — Special",
                "Generation 4 — Special",
                "Generation 4 — Special"
            ],
            "set": [
                "Move",
                "Type",
                "Cat.",
                "Power",
                "Acc.",
                "Method"
            ]
        }
    },
    "locations": [
        "We don't have any location data for Raikou yet."
    ]
}