{"id":"105","National №":"105","Type":["Fire","Ghost"],"Species":"Bone Keeper Pokémon","Height":"3′3″ (0.99m)","Weight":"75 lbs (34.0 kg)","Abilities":["Cursed Body","Lightning Rod"],"Local №":[],"Japanese":"Garagara","stats":{},"typeDef":{},"description":"The bone it holds is its key weapon. It throws the bone skillfully like a boomerang to KO targets.","moves":{"0":{"title":"Moves learnt by level up","Lv.":["1","1","1","1","3","7","11","13","17","21","23","27","33","37","43","49","53","59"],"Move":["Bone Club","Growl","Headbutt","Tail Whip","Tail Whip","Bone Club","Headbutt","Leer","Focus Energy","Bonemerang","Rage","False Swipe","Thrash","Fling","Bone Rush","Endeavor","Double-Edge","Retaliate"],"Type":["Ground","Normal","Normal","Normal","Normal","Ground","Normal","Normal","Normal","Ground","Normal","Normal","Normal","Dark","Ground","Normal","Normal","Normal"],"Cat.":["Physical","Status","Physical","Status","Status","Physical","Physical","Status","Status","Physical","Physical","Physical","Physical","Physical","Physical","Physical","Physical","Physical"],"Power":["65","-","70","-","-","65","70","-","-","50","20","40","120","-","25","-","120","70"],"Acc.":["85","100","100","100","100","85","100","100","-","90","100","100","100","100","90","100","100","100"],"set":["Lv.","Move","Type","Cat.","Power","Acc."]},"1":{"title":"Egg moves","Move":["Ancient Power","Belly Drum","Chip Away","Detect","Double Kick","Endure","Iron Head","Perish Song","Screech","Skull Bash"],"Type":["Rock","Normal","Normal","Fighting","Fighting","Normal","Steel","Normal","Normal","Normal"],"Cat.":["Special","Status","Physical","Status","Physical","Status","Physical","Status","Status","Physical"],"Power":["60","-","70","-","30","-","80","-","-","130"],"Acc.":["100","-","100","-","100","-","100","-","85","100"],"set":["Move","Type","Cat.","Power","Acc."]},"2":{"title":"Moves learnt by HM","HM":["4"],"Move":["Strength"],"Type":["Normal"],"Cat.":["Physical"],"Power":["80"],"Acc.":["100"],"set":["HM","Move","Type","Cat.","Power","Acc."]},"3":{"title":"Moves learnt by TM","TM":["6","10","11","13","14","15","17","21","23","26","27","28","31","32","35","37","38","39","40","42","44","45","46","48","49","52","54","56","59","67","68","71","75","78","80","87","88","90","94","98","100"],"Move":["Toxic","Hidden Power","Sunny Day","Ice Beam","Blizzard","Hyper Beam","Protect","Frustration","Smack Down","Earthquake","Return","Dig","Brick Break","Double Team","Flamethrower","Sandstorm","Fire Blast","Rock Tomb","Aerial Ace","Facade","Rest","Attract","Thief","Round","Echoed Voice","Focus Blast","False Swipe","Fling","Incinerate","Retaliate","Giga Impact","Stone Edge","Swords Dance","Bulldoze","Rock Slide","Swagger","Sleep Talk","Substitute","Rock Smash","Power-Up Punch","Confide"],"Type":["Poison","Normal","Fire","Ice","Ice","Normal","Normal","Normal","Rock","Ground","Normal","Ground","Fighting","Normal","Fire","Rock","Fire","Rock","Flying","Normal","Psychic","Normal","Dark","Normal","Normal","Fighting","Normal","Dark","Fire","Normal","Normal","Rock","Normal","Ground","Rock","Normal","Normal","Normal","Fighting","Fighting","Normal"],"Cat.":["Status","Special","Status","Special","Special","Special","Status","Physical","Physical","Physical","Physical","Physical","Physical","Status","Special","Status","Special","Physical","Physical","Physical","Status","Status","Physical","Special","Special","Special","Physical","Physical","Special","Physical","Physical","Physical","Status","Physical","Physical","Status","Status","Status","Physical","Physical","Status"],"Power":["-","60","-","90","110","150","-","-","50","100","-","80","75","-","90","-","110","60","60","70","-","-","60","60","40","120","40","-","60","70","150","100","-","60","75","-","-","-","40","40","-"],"Acc.":["90","100","-","100","70","90","-","100","100","100","100","100","100","-","100","-","85","95","∞","100","-","100","100","100","100","70","100","100","100","100","90","80","-","100","90","90","-","-","100","100","-"],"set":["TM","Move","Type","Cat.","Power","Acc."]},"4":{"title":"Transfer-only moves","Move":["Body Slam","Counter","Dynamic Punch","Mega Kick","Mega Punch","Mimic","Seismic Toss","Captivate","Natural Gift","Rock Climb","Fury Cutter","Mud-Slap"],"Type":["Normal","Fighting","Fighting","Normal","Normal","Normal","Fighting","Normal","Normal","Normal","Bug","Ground"],"Cat.":["Physical","Physical","Physical","Physical","Physical","Status","Physical","Status","Physical","Physical","Physical","Special"],"Power":["85","-","100","120","80","-","-","-","-","90","40","20"],"Acc.":["100","100","50","75","85","-","100","100","100","85","95","100"],"Method":["Generation 3 — Move tutor","Generation 3 — Move tutor","Generation 3 — Move tutor","Generation 3 — Move tutor","Generation 3 — Move tutor","Generation 3 — Move tutor","Generation 3 — Move tutor","Generation 4 — TM","Generation 4 — TM","Generation 4 — HM","Generation 4 — Move tutor","Generation 4 — Move tutor"],"set":["Move","Type","Cat.","Power","Acc.","Method"]}},"locations":[{"GoldSilver":["Rock Tunnel"],"Crystal":["Route 9","10"],"FireRedLeafGreen":["Seavault Canyon"],"HeartGoldSoulSilver":["Rock Tunnel"],"BlackWhite":["Route 15"]}]}