{"id":"314","National №":"314","Type":["Bug"],"Species":"Firefly Pokémon","Height":"2′0″ (0.61m)","Weight":"39 lbs (17.7 kg)","Abilities":["Oblivious","Tinted Lens"],"Local №":[],"Japanese":"Irumize","stats":{"HP":{"avg":"65","min":"240","max":"334"},"Attack":{"avg":"47","min":"89","max":"212"},"Defense":{"avg":"55","min":"103","max":"229"},"Sp. Atk":{"avg":"73","min":"135","max":"269"},"Sp. Def":{"avg":"75","min":"139","max":"273"},"Speed":{"avg":"85","min":"157","max":"295"}},"typeDef":{"Normal":"type-fx-cell type-fx-100","Fire":"type-fx-cell type-fx-200","Water":"type-fx-cell type-fx-100","Electric":"type-fx-cell type-fx-100","Grass":"type-fx-cell type-fx-50","Ice":"type-fx-cell type-fx-100","Fighting":"type-fx-cell type-fx-50","Poison":"type-fx-cell type-fx-100","Ground":"type-fx-cell type-fx-50","Flying":"type-fx-cell type-fx-200","Psychic":"type-fx-cell type-fx-100","Bug":"type-fx-cell type-fx-100","Rock":"type-fx-cell type-fx-200","Ghost":"type-fx-cell type-fx-100","Dragon":"type-fx-cell type-fx-100","Dark":"type-fx-cell type-fx-100","Steel":"type-fx-cell type-fx-100","Fairy":"type-fx-cell type-fx-100"},"description":"With its sweet aroma, it guides Volbeat to draw signs with light in the night sky.","moves":{"0":{"title":"Moves learnt by level up","Lv.":["1","1","5","9","13","17","21","25","29","33","37","41","45"],"Move":["Play Nice","Tackle","Sweet Scent","Charm","Moonlight","Quick Attack","Wish","Encore","Flatter","Helping Hand","Zen Headbutt","Bug Buzz","Covet"],"Type":["Normal","Normal","Normal","Fairy","Fairy","Normal","Normal","Normal","Dark","Normal","Psychic","Bug","Normal"],"Cat.":["Status","Physical","Status","Status","Status","Physical","Status","Status","Status","Status","Physical","Special","Physical"],"Power":["-","50","-","-","-","40","-","-","-","-","80","90","60"],"Acc.":["-","100","-","100","-","100","-","100","100","-","90","100","100"],"set":["Lv.","Move","Type","Cat.","Power","Acc."]},"1":{"title":"Egg moves","Move":["Baton Pass","Bug Buzz","Captivate","Confuse Ray","Encore","Fake Tears","Growth","Silver Wind"],"Type":["Normal","Bug","Normal","Ghost","Normal","Dark","Normal","Bug"],"Cat.":["Status","Special","Status","Status","Status","Status","Status","Special"],"Power":["-","90","-","-","-","-","-","60"],"Acc.":["-","100","100","100","100","100","-","100"],"set":["Move","Type","Cat.","Power","Acc."]},"2":{"title":"Moves learnt by HM","set":[]},"3":{"title":"Moves learnt by TM","TM":["6","10","11","16","17","18","19","21","22","24","25","27","30","31","32","40","42","44","45","46","48","56","57","62","70","73","76","77","87","88","89","90","98","99","100"],"Move":["Toxic","Hidden Power","Sunny Day","Light Screen","Protect","Rain Dance","Roost","Frustration","Solar Beam","Thunderbolt","Thunder","Return","Shadow Ball","Brick Break","Double Team","Aerial Ace","Facade","Rest","Attract","Thief","Round","Fling","Charge Beam","Acrobatics","Flash","Thunder Wave","Struggle Bug","Psych Up","Swagger","Sleep Talk","U-turn","Substitute","Power-Up Punch","Dazzling Gleam","Confide"],"Type":["Poison","Normal","Fire","Psychic","Normal","Water","Flying","Normal","Grass","Electric","Electric","Normal","Ghost","Fighting","Normal","Flying","Normal","Psychic","Normal","Dark","Normal","Dark","Electric","Flying","Normal","Electric","Bug","Normal","Normal","Normal","Bug","Normal","Fighting","Fairy","Normal"],"Cat.":["Status","Special","Status","Status","Status","Status","Status","Physical","Special","Special","Special","Physical","Special","Physical","Status","Physical","Physical","Status","Status","Physical","Special","Physical","Special","Physical","Status","Status","Special","Status","Status","Status","Physical","Status","Physical","Special","Status"],"Power":["-","60","-","-","-","-","-","-","120","90","110","-","80","75","-","60","70","-","-","60","60","-","50","55","-","-","50","-","-","-","70","-","40","80","-"],"Acc.":["90","100","-","-","-","-","-","100","100","100","70","100","100","100","-","∞","100","-","100","100","100","100","90","100","100","100","100","-","90","-","100","-","100","100","-"],"set":["TM","Move","Type","Cat.","Power","Acc."]},"4":{"title":"Transfer-only moves","Move":["Body Slam","Counter","Double-Edge","Dynamic Punch","Mega Kick","Mega Punch","Metronome","Mimic","Seismic Toss","Natural Gift","Air Cutter","Mud-Slap","Ominous Wind","String Shot","Swift"],"Type":["Normal","Fighting","Normal","Fighting","Normal","Normal","Normal","Normal","Fighting","Normal","Flying","Ground","Ghost","Bug","Normal"],"Cat.":["Physical","Physical","Physical","Physical","Physical","Physical","Status","Status","Physical","Physical","Special","Special","Special","Status","Special"],"Power":["85","-","120","100","120","80","-","-","-","-","60","20","60","-","60"],"Acc.":["100","100","100","50","75","85","-","-","100","100","95","100","100","95","∞"],"Method":["Generation 3 — Move tutor","Generation 3 — Move tutor","Generation 3 — Move tutor","Generation 3 — Move tutor","Generation 3 — Move tutor","Generation 3 — Move tutor","Generation 3 — Move tutor","Generation 3 — Move tutor","Generation 3 — Move tutor","Generation 4 — TM","Generation 4 — Move tutor","Generation 4 — Move tutor","Generation 4 — Move tutor","Generation 4 — Move tutor","Generation 4 — Move tutor"],"set":["Move","Type","Cat.","Power","Acc.","Method"]}},"locations":[{"RubySapphire":["Route 117"],"Emerald":["Route 117"],"DiamondPearl":["Route 229"],"Platinum":["Route 229"],"HeartGoldSoulSilver":["National Park"],"BlackWhite":["Route 3"],"XY":["Route 7 (Rivière Walk)"],"Omega RubyAlpha Sapphire":["Route 117"]}]}